pyeasytrend/__init__.py
pyEasyTrend-0.0.0.7.dist-info/LICENSE
pyEasyTrend-0.0.0.7.dist-info/METADATA
pyEasyTrend-0.0.0.7.dist-info/WHEEL
pyEasyTrend-0.0.0.7.dist-info/top_level.txt
pyEasyTrend-0.0.0.7.dist-info/RECORD
